fastsecure/__init__.py
fastsecure/core/__init__.py
fastsecure/core/manager.py
fastsecure/core/strategies.py
fastsecure/core/types.py
fastsecure/dependencies/__init__.py
fastsecure/dependencies/auth.py
fastsecure/exceptions/__init__.py
fastsecure/exceptions/auth.py
fastsecure/middleware/__init__.py
fastsecure/middleware/auth.py
fastsecure/providers/__init__.py
fastsecure/providers/base.py
fastsecure/providers/jwt.py
fastsecure/providers/session.py
fastsecure/providers/oauth/__init__.py
fastsecure/providers/oauth/base.py
fastsecure/providers/oauth/github.py
fastsecure/providers/oauth/google.py
fastsecure/providers/storage/__init__.py
fastsecure/providers/storage/base.py
fastsecure/providers/storage/db.py
fastsecure/providers/storage/memory.py
fastsecure/providers/storage/redis.py
fastsecure-0.1.0.dist-info/METADATA
fastsecure-0.1.0.dist-info/WHEEL
fastsecure-0.1.0.dist-info/top_level.txt
fastsecure-0.1.0.dist-info/RECORD
