Metadata-Version: 2.2
Name: fastsecure
Version: 0.1.0
Summary: Flexible authentication system for FastAPI applications
Author-email: Igor Benav <igor.magalhaes.r@gmail.com>
Keywords: fastapi,authentication,oauth,jwt,session
Classifier: Development Status :: 3 - Alpha
Classifier: Framework :: FastAPI
Classifier: Intended Audience :: Developers
Classifier: License :: OSI Approved :: MIT License
Classifier: Programming Language :: Python :: 3
Classifier: Programming Language :: Python :: 3.9
Classifier: Programming Language :: Python :: 3.10
Classifier: Programming Language :: Python :: 3.11
Classifier: Topic :: Security
Requires-Python: >=3.9
Requires-Dist: fastapi>=0.115.8
Requires-Dist: httpx>=0.28.1
Requires-Dist: pydantic>=2.10.6
Requires-Dist: python-jose[cryptography]>=3.3.0
Requires-Dist: python-multipart>=0.0.20
Requires-Dist: redis>=5.2.1
Requires-Dist: sqlalchemy>=2.0.37
